README.txt
setup.py
lookup/__init__.py
lookup/__init__.pyc
lookup/models.py
lookup/models.pyc
lookup/tests.py
lookup/management/__init__.py
lookup/management/commands/__init__.py
lookup/management/commands/lookup_clean.py
lookup/management/commands/lookup_init.py
unholster.django_lookup.egg-info/PKG-INFO
unholster.django_lookup.egg-info/SOURCES.txt
unholster.django_lookup.egg-info/dependency_links.txt
unholster.django_lookup.egg-info/requires.txt
unholster.django_lookup.egg-info/top_level.txt