Metadata-Version: 1.1
Name: unholster.django-lookup
Version: 0.1.0
Summary: Easy SlugField management
Home-page: https://github.com/Unholster/django-lookup
Author: Andrés Villavicencio
Author-email: andres@unholster.com
License: MIT License
Platform: UNKNOWN
Classifier: Development Status :: 5 - Production/Stable
Classifier: Topic :: Utilities
